adiscstudies/__init__.py
adiscstudies/entities.tsv
adiscstudies/fields.tsv
adiscstudies/properties.tsv
adiscstudies/schema.owl
adiscstudies/schema.sql
adiscstudies/schema_with_labels.sql
adiscstudies/tables.tsv
adiscstudies/values.tsv
adiscstudies/verbalizations.txt.jinja
adiscstudies/scripts/__init__.py
adiscstudies/scripts/adiscstudies.py
adiscstudies-1.0.0.dist-info/METADATA
adiscstudies-1.0.0.dist-info/WHEEL
adiscstudies-1.0.0.dist-info/entry_points.txt
adiscstudies-1.0.0.dist-info/top_level.txt
adiscstudies-1.0.0.dist-info/RECORD
