Metadata-Version: 2.4
Name: adiscstudies
Version: 1.0.0
Summary: Single cell studies data model
Classifier: Topic :: Scientific/Engineering
Classifier: Intended Audience :: Science/Research
